redis_semaphore_eval/__init__.py
redis_semaphore_eval-0.3.0.dist-info/LICENSE.md
redis_semaphore_eval-0.3.0.dist-info/WHEEL
redis_semaphore_eval-0.3.0.dist-info/METADATA
redis_semaphore_eval-0.3.0.dist-info/RECORD
