Metadata-Version: 2.1
Name: redis-semaphore-eval
Version: 0.3.0
Summary: A redis semaphore implementation using eval scripts
Home-page: https://github.com/wakemaster39/redis-semaphore-eval
License: MIT
Keywords: redis,semaphore,lock
Author: Cameron HUrst
Author-email: cameron.a.hurst@gmail.com
Requires-Python: >=3.6.1,<4.0.0
Classifier: License :: OSI Approved :: MIT License
Classifier: Programming Language :: Python :: 3
Classifier: Programming Language :: Python :: 3.7
Classifier: Programming Language :: Python :: 3.8
Classifier: Programming Language :: Python :: 3.9
Requires-Dist: redis (>=3.5.3,<4.0.0)
Project-URL: Repository, https://github.com/wakemaster39/redis-semaphore-eval
